gaia/__init__.py
gaia/client.py
gaia-0.0.9.data/scripts/launch-sisyphus.sh
gaia-0.0.9.dist-info/METADATA
gaia-0.0.9.dist-info/RECORD
gaia-0.0.9.dist-info/WHEEL
gaia-0.0.9.dist-info/top_level.txt
