Metadata-Version: 2.1
Name: gaia
Version: 0.0.9
Summary: UNKNOWN
Home-page: https://github.com/prismofeverything/gaia
Author: Ryan Spangler
Author-email: ryan.spangler@gmail.com
License: MIT
Platform: UNKNOWN
Requires-Dist: requests
Requires-Dist: pyyaml
